omnivook/__init__.py
omnivook/source_template/conf.py
omnivook/source_template/index.md
omnivook-0.1.6.dist-info/METADATA
omnivook-0.1.6.dist-info/WHEEL
omnivook-0.1.6.dist-info/entry_points.txt
omnivook-0.1.6.dist-info/top_level.txt
omnivook-0.1.6.dist-info/RECORD
