Metadata-Version: 2.1
Name: omnivook
Version: 0.1.6
Summary: A tool to generate ebooks from Omnivore articles
Requires-Dist: omnivoreql
Requires-Dist: sphinx
Requires-Dist: rich
Requires-Dist: myst-parser
